setup.py
tests/__init__.py
tests/base.py
tests/test_version.py
zametki/__init__.py
zametki/cli.py
zametki/generate.py
zametki/post.py
zametki/server.py
zametki/version.py
zametki/zametkiproject.py
zametki.egg-info/PKG-INFO
zametki.egg-info/SOURCES.txt
zametki.egg-info/dependency_links.txt
zametki.egg-info/entry_points.txt
zametki.egg-info/requires.txt
zametki.egg-info/top_level.txt