Metadata-Version: 1.1
Name: zametki
Version: 0.1.0
Summary: A python package for writing logs
Home-page: https://github.com/Mechasparrow/zametki
Author: Michael Navazhylau
Author-email: mikipux7@gmail.com
License: MIT
Keywords: brain mind search
Platform: UNKNOWN
Classifier: Development Status :: 4 - Beta
Classifier: Intended Audience :: Developers
Classifier: License :: OSI Approved :: MIT License
Classifier: Natural Language :: English
Classifier: Operating System :: Unix
Classifier: Programming Language :: Python :: 3.2
Classifier: Programming Language :: Python :: Implementation :: PyPy
Classifier: Operating System :: OS Independent
